[{"ItemCode": "643", "ParentCode": "6", "Item": {"Code": "643", "Name": "Russian Federation", "ParentCode": 6, "Parent": {"Code": "6", "Name": "East Europe & Central Asia", "ParentCode": 0, "Color": "#C0392B"}}, "Value": 80361.308123, "ExportValue": 11233.333333, "RealizedPotential": 0.1397853469, "LineLength": 61.979813657, "BubbleSize": 258834.06485, "LineWidth": 3.2981018751, "Ta": 0.0, "Stability": 0.0, "Tariff": 0.54, "Xik": 9571733.3333, "Mjk": 244866.66667, "Xij": 19097717667.0, "EpiMreg": 364359.28246, "BubbleSizeMreg": 1663750.6349, "LineWithMreg": 0.0035333881, "Gap": 0.8602146531, "Rank": 1}, {"ItemCode": "616", "ParentCode": "4", "Item": {"Code": "616", "Name": "Poland", "ParentCode": 4, "Parent": {"Code": "4", "Name": "EU & West Europe", "ParentCode": 0, "Color": "#3d8fc3"}}, "Value": 47293.734656, "ExportValue": 10500.0, "RealizedPotential": 0.2220167233, "LineLength": 37.489558072, "BubbleSize": 316761.07196, "LineWidth": 2.6221060539, "Ta": 0.0, "Stability": 0.0, "Tariff": 0.54, "Xik": 6590933.3333, "Mjk": 244866.66667, "Xij": 3144988300.0, "EpiMreg": 146514.23553, "BubbleSizeMreg": 1803600.14, "LineWithMreg": 0.002166852, "Gap": 0.7779832767, "Rank": 2}, {"ItemCode": "124", "ParentCode": "10", "Item": {"Code": "124", "Name": "Canada", "ParentCode": 10, "Parent": {"Code": "10", "Name": "North America", "ParentCode": 0, "Color": "#d9b015"}}, "Value": 29010.224788, "ExportValue": 433.33333333, "RealizedPotential": 0.0149372622, "LineLength": 575.04857656, "BubbleSize": 63437.588451, "LineWidth": 0.5235867695, "Ta": 0.0, "Stability": 0.0, "Tariff": 0.54, "Xik": 91987233.333, "Mjk": 244866.66667, "Xij": 1300470366.7, "EpiMreg": 540663.37443, "BubbleSizeMreg": 854591.77153, "LineWithMreg": 0.0011001799, "Gap": 0.9850627378, "Rank": 3}, {"ItemCode": "276", "ParentCode": "4", "Item": {"Code": "276", "Name": "Germany", "ParentCode": 4, "Parent": {"Code": "4", "Name": "EU & West Europe", "ParentCode": 0, "Color": "#3d8fc3"}}, "Value": 28019.546028, "ExportValue": 2533.3333333, "RealizedPotential": 0.0904130756, "LineLength": 37.842671812, "BubbleSize": 257397.69991, "LineWidth": 1.8939277579, "Ta": 0.0, "Stability": 0.0, "Tariff": 0.54, "Xik": 6518833.3333, "Mjk": 244866.66667, "Xij": 22410874333.0, "EpiMreg": 146504.83438, "BubbleSizeMreg": 1643727.1554, "LineWithMreg": 0.0023552686, "Gap": 0.9095869244, "Rank": 4}, {"ItemCode": "826", "ParentCode": "4", "Item": {"Code": "826", "Name": "United Kingdom", "ParentCode": 4, "Parent": {"Code": "4", "Name": "EU & West Europe", "ParentCode": 0, "Color": "#3d8fc3"}}, "Value": 25342.236325, "ExportValue": 29533.333333, "RealizedPotential": 1.0, "LineLength": 43.149351661, "BubbleSize": 189062.28019, "LineWidth": 2.0452883202, "Ta": 0.0, "Stability": 0.0, "Tariff": 0.54, "Xik": 7017400.0, "Mjk": 244866.66667, "Xij": 7882556000.0, "EpiMreg": 241616.46258, "BubbleSizeMreg": 1448739.9916, "LineWithMreg": 0.0038651095, "Gap": 0.0, "Rank": 5}, {"ItemCode": "381", "ParentCode": "4", "Item": {"Code": "381", "Name": "Italy", "ParentCode": 4, "Parent": {"Code": "4", "Name": "EU & West Europe", "ParentCode": 0, "Color": "#3d8fc3"}}, "Value": 19691.173217, "ExportValue": 0.0, "RealizedPotential": 0.0, "LineLength": 12.298324664, "BubbleSize": 317184.47406, "LineWidth": 3.3235520586, "Ta": 0.0, "Stability": 0.0, "Tariff": 0.54, "Xik": 2260666.6667, "Mjk": 244866.66667, "Xij": 10742569267.0, "EpiMreg": 91056.138023, "BubbleSizeMreg": 1791847.1013, "LineWithMreg": 0.0041320191, "Gap": 1.0, "Rank": 6}, {"ItemCode": "398", "ParentCode": "6", "Item": {"Code": "398", "Name": "Kazakhstan", "ParentCode": 6, "Parent": {"Code": "6", "Name": "East Europe & Central Asia", "ParentCode": 0, "Color": "#C0392B"}}, "Value": 19216.048732, "ExportValue": 76866.666667, "RealizedPotential": 1.0, "LineLength": 14.626081865, "BubbleSize": 169892.97948, "LineWidth": 5.0915431245, "Ta": 0.0, "Stability": 0.0, "Tariff": 0.54, "Xik": 2678900.0, "Mjk": 244866.66667, "Xij": 1269220833.3, "EpiMreg": 28138.107725, "BubbleSizeMreg": 1453850.0995, "LineWithMreg": 0.0013232663, "Gap": 0.0, "Rank": 7}, {"ItemCode": "251", "ParentCode": "4", "Item": {"Code": "251", "Name": "France", "ParentCode": 4, "Parent": {"Code": "4", "Name": "EU & West Europe", "ParentCode": 0, "Color": "#3d8fc3"}}, "Value": 11950.07287, "ExportValue": 866.66666667, "RealizedPotential": 0.072523965, "LineLength": 21.978071119, "BubbleSize": 225158.20671, "LineWidth": 1.5899445045, "Ta": 0.0, "Stability": 0.0, "Tariff": 0.54, "Xik": 3580633.3333, "Mjk": 244866.66667, "Xij": 7527156633.3, "EpiMreg": 84690.961536, "BubbleSizeMreg": 1585607.3024, "LineWithMreg": 0.002430255, "Gap": 0.927476035, "Rank": 8}, {"ItemCode": "804", "ParentCode": "6", "Item": {"Code": "804", "Name": "Ukraine", "ParentCode": 6, "Parent": {"Code": "6", "Name": "East Europe & Central Asia", "ParentCode": 0, "Color": "#C0392B"}}, "Value": 7684.6079898, "ExportValue": 15033.333333, "RealizedPotential": 1.0, "LineLength": 6.926666402, "BubbleSize": 205260.91372, "LineWidth": 3.5586064048, "Ta": 1.0, "Stability": 0.0, "Tariff": 0.54, "Xik": 961100.0, "Mjk": 244866.66667, "Xij": 2674453166.7, "EpiMreg": 62270.071001, "BubbleSizeMreg": 1664527.0426, "LineWithMreg": 0.0054008763, "Gap": 0.0, "Rank": 9}, {"ItemCode": "56", "ParentCode": "4", "Item": {"Code": "56", "Name": "Belgium", "ParentCode": 4, "Parent": {"Code": "4", "Name": "EU & West Europe", "ParentCode": 0, "Color": "#3d8fc3"}}, "Value": 6171.5148914, "ExportValue": 166.66666667, "RealizedPotential": 0.0270057951, "LineLength": 14.595203492, "BubbleSize": 222423.40321, "LineWidth": 1.2516702016, "Ta": 0.0, "Stability": 0.0, "Tariff": 0.54, "Xik": 2558466.6667, "Mjk": 244866.66667, "Xij": 4538760433.3, "EpiMreg": 49904.938648, "BubbleSizeMreg": 1559024.7833, "LineWithMreg": 0.0021932107, "Gap": 0.9729942049, "Rank": 10}, {"ItemCode": "191", "ParentCode": "4", "Item": {"Code": "191", "Name": "Croatia", "ParentCode": 4, "Parent": {"Code": "4", "Name": "EU & West Europe", "ParentCode": 0, "Color": "#3d8fc3"}}, "Value": 5678.5439583, "ExportValue": 81100.0, "RealizedPotential": 1.0, "LineLength": 5.713333346, "BubbleSize": 264659.89974, "LineWidth": 2.4725669074, "Ta": 0.0, "Stability": 0.0, "Tariff": 0.54, "Xik": 1549700.0, "Mjk": 244866.66667, "Xij": 179524566.67, "EpiMreg": 28141.809457, "BubbleSizeMreg": 1722198.7701, "LineWithMreg": 0.0028600866, "Gap": 0.0, "Rank": 11}, {"ItemCode": "842", "ParentCode": "10", "Item": {"Code": "842", "Name": "United States of America", "ParentCode": 10, "Parent": {"Code": "10", "Name": "North America", "ParentCode": 0, "Color": "#d9b015"}}, "Value": 4965.0892326, "ExportValue": 7333.3333333, "RealizedPotential": 1.0, "LineLength": 39.445041737, "BubbleSize": 56846.230518, "LineWidth": 1.4578798521, "Ta": 0.0, "Stability": 0.0, "Tariff": 0.54, "Xik": 6274766.6667, "Mjk": 244866.66667, "Xij": 10834603533.0, "EpiMreg": 162534.26351, "BubbleSizeMreg": 778857.5904, "LineWithMreg": 0.0052904724, "Gap": 0.0, "Rank": 12}, {"ItemCode": "699", "ParentCode": "13", "Item": {"Code": "699", "Name": "India", "ParentCode": 13, "Parent": {"Code": "13", "Name": "South Asia", "ParentCode": 0, "Color": "#dac20c"}}, "Value": 4142.867336, "ExportValue": 0.0, "RealizedPotential": 0.0, "LineLength": 13.667972706, "BubbleSize": 117135.56306, "LineWidth": 1.7037149011, "Ta": 1.0, "Stability": 0.0, "Tariff": 0.54, "Xik": 1665500.0, "Mjk": 244866.66667, "Xij": 5738083500.0, "EpiMreg": 119536.019, "BubbleSizeMreg": 1343803.6616, "LineWithMreg": 0.0065081696, "Gap": 1.0, "Rank": 13}, {"ItemCode": "348", "ParentCode": "4", "Item": {"Code": "348", "Name": "Hungary", "ParentCode": 4, "Parent": {"Code": "4", "Name": "EU & West Europe", "ParentCode": 0, "Color": "#3d8fc3"}}, "Value": 3817.1994286, "ExportValue": 0.0, "RealizedPotential": 0.0, "LineLength": 4.1150380949, "BubbleSize": 248346.20309, "LineWidth": 2.4592474704, "Ta": 0.0, "Stability": 0.0, "Tariff": 0.54, "Xik": 592566.66667, "Mjk": 244866.66667, "Xij": 1584136133.3, "EpiMreg": 14900.985018, "BubbleSizeMreg": 1702559.1883, "LineWithMreg": 0.00212686, "Gap": 1.0, "Rank": 14}, {"ItemCode": "504", "ParentCode": "11", "Item": {"Code": "504", "Name": "Morocco", "ParentCode": 11, "Parent": {"Code": "11", "Name": "Northern Africa", "ParentCode": 0, "Color": "#34495E"}}, "Value": 3104.2630534, "ExportValue": 0.0, "RealizedPotential": 0.0, "LineLength": 3.4008155723, "BubbleSize": 157168.73216, "LineWidth": 3.8238253971, "Ta": 1.0, "Stability": 0.0, "Tariff": 0.54, "Xik": 398633.33333, "Mjk": 244866.66667, "Xij": 732193566.67, "EpiMreg": 13478.425982, "BubbleSizeMreg": 1412557.1588, "LineWithMreg": 0.0028057571, "Gap": 1.0, "Rank": 15}, {"ItemCode": "246", "ParentCode": "4", "Item": {"Code": "246", "Name": "Finland", "ParentCode": 4, "Parent": {"Code": "4", "Name": "EU & West Europe", "ParentCode": 0, "Color": "#3d8fc3"}}, "Value": 2531.2094616, "ExportValue": 566.66666667, "RealizedPotential": 0.2238718981, "LineLength": 5.4854679719, "BubbleSize": 221811.08427, "LineWidth": 1.3696825555, "Ta": 0.0, "Stability": 0.0, "Tariff": 0.54, "Xik": 962000.0, "Mjk": 244866.66667, "Xij": 900074766.67, "EpiMreg": 19054.651319, "BubbleSizeMreg": 1534229.884, "LineWithMreg": 0.0022641067, "Gap": 0.7761281019, "Rank": 16}, {"ItemCode": "528", "ParentCode": "4", "Item": {"Code": "528", "Name": "Netherlands", "ParentCode": 4, "Parent": {"Code": "4", "Name": "EU & West Europe", "ParentCode": 0, "Color": "#3d8fc3"}}, "Value": 2480.614679, "ExportValue": 0.0, "RealizedPotential": 0.0, "LineLength": 5.8645685609, "BubbleSize": 222268.37021, "LineWidth": 1.2529517418, "Ta": 0.0, "Stability": 0.0, "Tariff": 0.54, "Xik": 1671200.0, "Mjk": 244866.66667, "Xij": 4945112933.3, "EpiMreg": 22645.140141, "BubbleSizeMreg": 1553826.2848, "LineWithMreg": 0.0024850577, "Gap": 1.0, "Rank": 17}, {"ItemCode": "208", "ParentCode": "4", "Item": {"Code": "208", "Name": "Denmark", "ParentCode": 4, "Parent": {"Code": "4", "Name": "EU & West Europe", "ParentCode": 0, "Color": "#3d8fc3"}}, "Value": 2147.3704999, "ExportValue": 0.0, "RealizedPotential": 0.0, "LineLength": 6.1768924112, "BubbleSize": 233249.11152, "LineWidth": 0.9813088495, "Ta": 0.0, "Stability": 0.0, "Tariff": 0.54, "Xik": 1061300.0, "Mjk": 244866.66667, "Xij": 796772166.67, "EpiMreg": 22550.527989, "BubbleSizeMreg": 1570510.5395, "LineWithMreg": 0.0023245871, "Gap": 1.0, "Rank": 18}, {"ItemCode": "710", "ParentCode": "14", "Item": {"Code": "710", "Name": "South Africa", "ParentCode": 14, "Parent": {"Code": "14", "Name": "Southern Africa", "ParentCode": 0, "Color": "#DB4C60"}}, "Value": 1892.69556, "ExportValue": 0.0, "RealizedPotential": 0.0, "LineLength": 9.9444182991, "BubbleSize": 71057.336548, "LineWidth": 1.7635233825, "Ta": 1.0, "Stability": 0.0, "Tariff": 0.54, "Xik": 1760766.6667, "Mjk": 244866.66667, "Xij": 904842100.0, "EpiMreg": 23168.213342, "BubbleSizeMreg": 1085277.198, "LineWithMreg": 0.0021467056, "Gap": 1.0, "Rank": 19}, {"ItemCode": "440", "ParentCode": "4", "Item": {"Code": "440", "Name": "Lithuania", "ParentCode": 4, "Parent": {"Code": "4", "Name": "EU & West Europe", "ParentCode": 0, "Color": "#3d8fc3"}}, "Value": 1732.4130115, "ExportValue": 0.0, "RealizedPotential": 0.0, "LineLength": 3.3089416095, "BubbleSize": 296972.4141, "LineWidth": 1.1607401094, "Ta": 0.0, "Stability": 0.0, "Tariff": 0.54, "Xik": 509000.0, "Mjk": 244866.66667, "Xij": 331353566.67, "EpiMreg": 9249.5725771, "BubbleSizeMreg": 1733219.0972, "LineWithMreg": 0.0016127947, "Gap": 1.0, "Rank": 20}, {"ItemCode": "410", "ParentCode": "5", "Item": {"Code": "410", "Name": "Korea, Republic of", "ParentCode": 5, "Parent": {"Code": "5", "Name": "East Asia", "ParentCode": 0, "Color": "#d8a618"}}, "Value": 1375.9067194, "ExportValue": 533.33333333, "RealizedPotential": 0.3876231766, "LineLength": 6.1719832051, "BubbleSize": 68545.847083, "LineWidth": 2.1412721871, "Ta": 0.0, "Stability": 0.0, "Tariff": 0.54, "Xik": 2630800.0, "Mjk": 244866.66667, "Xij": 6291794100.0, "EpiMreg": 24090.492901, "BubbleSizeMreg": 995776.72416, "LineWithMreg": 0.0039197555, "Gap": 0.6123768234, "Rank": 21}, {"ItemCode": "688", "ParentCode": "6", "Item": {"Code": "688", "Name": "Serbia", "ParentCode": 6, "Parent": {"Code": "6", "Name": "East Europe & Central Asia", "ParentCode": 0, "Color": "#C0392B"}}, "Value": 1266.4701826, "ExportValue": 0.0, "RealizedPotential": 0.0, "LineLength": 1.1772986519, "BubbleSize": 190184.3821, "LineWidth": 3.7241077719, "Ta": 0.0, "Stability": 0.0, "Tariff": 0.54, "Xik": 159433.33333, "Mjk": 244866.66667, "Xij": 305766166.67, "EpiMreg": 2619.7005579, "BubbleSizeMreg": 1627316.4101, "LineWithMreg": 0.0013673919, "Gap": 1.0, "Rank": 22}, {"ItemCode": "784", "ParentCode": "9", "Item": {"Code": "784", "Name": "United Arab Emirates", "ParentCode": 9, "Parent": {"Code": "9", "Name": "Middle East", "ParentCode": 0, "Color": "#b69118"}}, "Value": 1206.3164495, "ExportValue": 0.0, "RealizedPotential": 0.0, "LineLength": 3.242977351, "BubbleSize": 203478.78792, "LineWidth": 1.2036132505, "Ta": 0.0, "Stability": 0.0, "Tariff": 0.54, "Xik": 448766.66667, "Mjk": 244866.66667, "Xij": 3997229433.3, "EpiMreg": 279841.46908, "BubbleSizeMreg": 882883.15509, "LineWithMreg": 0.0977383326, "Gap": 1.0, "Rank": 23}, {"ItemCode": "203", "ParentCode": "4", "Item": {"Code": "203", "Name": "Czechia", "ParentCode": 4, "Parent": {"Code": "4", "Name": "EU & West Europe", "ParentCode": 0, "Color": "#3d8fc3"}}, "Value": 1161.1221537, "ExportValue": 0.0, "RealizedPotential": 0.0, "LineLength": 0.9498748423, "BubbleSize": 323855.66327, "LineWidth": 2.4851282009, "Ta": 0.0, "Stability": 0.0, "Tariff": 0.54, "Xik": 210433.33333, "Mjk": 244866.66667, "Xij": 2386876700.0, "EpiMreg": 4690.93811, "BubbleSizeMreg": 1806600.5307, "LineWithMreg": 0.0027335762, "Gap": 1.0, "Rank": 24}, {"ItemCode": "724", "ParentCode": "4", "Item": {"Code": "724", "Name": "Spain", "ParentCode": 4, "Parent": {"Code": "4", "Name": "EU & West Europe", "ParentCode": 0, "Color": "#3d8fc3"}}, "Value": 939.24740022, "ExportValue": 0.0, "RealizedPotential": 0.0, "LineLength": 1.4213529707, "BubbleSize": 188119.87397, "LineWidth": 2.3127684211, "Ta": 0.0, "Stability": 0.0, "Tariff": 0.54, "Xik": 301100.0, "Mjk": 244866.66667, "Xij": 5832224600.0, "EpiMreg": 6257.5012913, "BubbleSizeMreg": 1495077.6559, "LineWithMreg": 0.0029446607, "Gap": 1.0, "Rank": 25}, {"ItemCode": "40", "ParentCode": "4", "Item": {"Code": "40", "Name": "Austria", "ParentCode": 4, "Parent": {"Code": "4", "Name": "EU & West Europe", "ParentCode": 0, "Color": "#3d8fc3"}}, "Value": 870.34789415, "ExportValue": 33.333333333, "RealizedPotential": 0.0382988614, "LineLength": 1.40490863, "BubbleSize": 305453.26557, "LineWidth": 1.3353305896, "Ta": 0.0, "Stability": 0.0, "Tariff": 0.54, "Xik": 307400.0, "Mjk": 244866.66667, "Xij": 1517615633.3, "EpiMreg": 4778.6119918, "BubbleSizeMreg": 1783863.3886, "LineWithMreg": 0.0019067427, "Gap": 0.9617011386, "Rank": 26}, {"ItemCode": "752", "ParentCode": "4", "Item": {"Code": "752", "Name": "Sweden", "ParentCode": 4, "Parent": {"Code": "4", "Name": "EU & West Europe", "ParentCode": 0, "Color": "#3d8fc3"}}, "Value": 763.1273249, "ExportValue": 0.0, "RealizedPotential": 0.0, "LineLength": 2.1978698614, "BubbleSize": 224413.64059, "LineWidth": 1.0186724181, "Ta": 0.0, "Stability": 0.0, "Tariff": 0.54, "Xik": 452833.33333, "Mjk": 244866.66667, "Xij": 1609933133.3, "EpiMreg": 6387.4513582, "BubbleSizeMreg": 1542156.0411, "LineWithMreg": 0.0018845051, "Gap": 1.0, "Rank": 27}, {"ItemCode": "764", "ParentCode": "1", "Item": {"Code": "764", "Name": "Thailand", "ParentCode": 1, "Parent": {"Code": "1", "Name": "ASEAN", "ParentCode": 0, "Color": "#54A2C9"}}, "Value": 484.44964008, "ExportValue": 0.0, "RealizedPotential": 0.0, "LineLength": 3.8922729312, "BubbleSize": 75343.203352, "LineWidth": 1.0876521893, "Ta": 0.0, "Stability": 0.0, "Tariff": 0.54, "Xik": 564533.33333, "Mjk": 244866.66667, "Xij": 1317646833.3, "EpiMreg": 12763.696159, "BubbleSizeMreg": 1021945.8785, "LineWithMreg": 0.0032088194, "Gap": 1.0, "Rank": 28}, {"ItemCode": "36", "ParentCode": "12", "Item": {"Code": "36", "Name": "Australia", "ParentCode": 12, "Parent": {"Code": "12", "Name": "Pacific", "ParentCode": 0, "Color": "#309d6d"}}, "Value": 311.79965698, "ExportValue": 0.0, "RealizedPotential": 0.0, "LineLength": 4.9088274308, "BubbleSize": 38503.99504, "LineWidth": 1.0861275837, "Ta": 0.0, "Stability": 0.0, "Tariff": 0.54, "Xik": 759200.0, "Mjk": 244866.66667, "Xij": 868912833.33, "EpiMreg": 14727.067186, "BubbleSizeMreg": 720915.85308, "LineWithMreg": 0.0041615386, "Gap": 1.0, "Rank": 29}]