[{"ItemCode": "586", "ParentCode": "13", "Item": {"Code": "586", "Name": "Pakistan", "ParentCode": 13, "Parent": {"Code": "13", "Name": "South Asia", "ParentCode": 0, "Color": "#dac20c"}}, "Value": 179750.9047, "ExportValue": 54800.0, "RealizedPotential": 0.3048663376, "LineLength": 92.939327682, "BubbleSize": 407630.97064, "LineWidth": 2.2895407904, "Ta": 0.0, "Stability": 0.0, "Tariff": 0.15, "Xik": 126328400.0, "Mjk": 1628216.6667, "Xij": 20795800.0, "EpiMreg": 792844.37555, "BubbleSizeMreg": 2835326.3881, "LineWithMreg": 0.0030087449, "Gap": 0.6951336624, "Rank": 1}, {"ItemCode": "156", "ParentCode": "5", "Item": {"Code": "156", "Name": "China", "ParentCode": 5, "Parent": {"Code": "5", "Name": "East Asia", "ParentCode": 0, "Color": "#d8a618"}}, "Value": 119074.89978, "ExportValue": 0.0, "RealizedPotential": 0.0, "LineLength": 118.48771306, "BubbleSize": 499567.7878, "LineWidth": 0.9707255937, "Ta": 0.0, "Stability": 0.0, "Tariff": 0.15, "Xik": 129892000.0, "Mjk": 1628216.6667, "Xij": 658138166.67, "EpiMreg": 1017935.6145, "BubbleSizeMreg": 2855259.1964, "LineWithMreg": 0.0030088563, "Gap": 1.0, "Rank": 2}, {"ItemCode": "842", "ParentCode": "10", "Item": {"Code": "842", "Name": "United States of America", "ParentCode": 10, "Parent": {"Code": "10", "Name": "North America", "ParentCode": 0, "Color": "#d9b015"}}, "Value": 74844.575342, "ExportValue": 0.0, "RealizedPotential": 0.0, "LineLength": 83.193763214, "BubbleSize": 281695.2634, "LineWidth": 1.5411113333, "Ta": 0.0, "Stability": 0.0, "Tariff": 0.15, "Xik": 127827866.67, "Mjk": 1628216.6667, "Xij": 501090166.67, "EpiMreg": 340750.51766, "BubbleSizeMreg": 1734337.7198, "LineWithMreg": 0.0023616312, "Gap": 1.0, "Rank": 3}, {"ItemCode": "381", "ParentCode": "4", "Item": {"Code": "381", "Name": "Italy", "ParentCode": 4, "Parent": {"Code": "4", "Name": "EU & West Europe", "ParentCode": 0, "Color": "#3d8fc3"}}, "Value": 60515.956629, "ExportValue": 833.33333333, "RealizedPotential": 0.0137704728, "LineLength": 36.490950186, "BubbleSize": 523363.51292, "LineWidth": 1.5290626814, "Ta": 0.0, "Stability": 0.0, "Tariff": 0.15, "Xik": 72158433.333, "Mjk": 1628216.6667, "Xij": 403777566.67, "EpiMreg": 494988.35486, "BubbleSizeMreg": 2879527.4954, "LineWithMreg": 0.004710734, "Gap": 0.9862295272, "Rank": 4}, {"ItemCode": "764", "ParentCode": "1", "Item": {"Code": "764", "Name": "Thailand", "ParentCode": 1, "Parent": {"Code": "1", "Name": "ASEAN", "ParentCode": 0, "Color": "#54A2C9"}}, "Value": 42302.039544, "ExportValue": 727400.0, "RealizedPotential": 1.0, "LineLength": 98.653418797, "BubbleSize": 501471.97088, "LineWidth": 0.4126164165, "Ta": 0.0, "Stability": 0.0, "Tariff": 0.15, "Xik": 110815533.33, "Mjk": 1628216.6667, "Xij": 20237266.667, "EpiMreg": 298275.56548, "BubbleSizeMreg": 2712876.8242, "LineWithMreg": 0.0011144882, "Gap": 0.0, "Rank": 5}, {"ItemCode": "724", "ParentCode": "4", "Item": {"Code": "724", "Name": "Spain", "ParentCode": 4, "Parent": {"Code": "4", "Name": "EU & West Europe", "ParentCode": 0, "Color": "#3d8fc3"}}, "Value": 32219.566096, "ExportValue": 466.66666667, "RealizedPotential": 0.0144839526, "LineLength": 34.176014913, "BubbleSize": 676842.48333, "LineWidth": 0.6721321302, "Ta": 0.0, "Stability": 0.0, "Tariff": 0.15, "Xik": 64498033.333, "Mjk": 1628216.6667, "Xij": 66078000.0, "EpiMreg": 174365.31421, "BubbleSizeMreg": 2987363.5022, "LineWithMreg": 0.0017078535, "Gap": 0.9855160474, "Rank": 6}, {"ItemCode": "704", "ParentCode": "1", "Item": {"Code": "704", "Name": "Viet Nam", "ParentCode": 1, "Parent": {"Code": "1", "Name": "ASEAN", "ParentCode": 0, "Color": "#54A2C9"}}, "Value": 31606.050182, "ExportValue": 0.0, "RealizedPotential": 0.0, "LineLength": 44.325273848, "BubbleSize": 464025.47526, "LineWidth": 0.7415167636, "Ta": 0.0, "Stability": 0.0, "Tariff": 0.15, "Xik": 48547966.667, "Mjk": 1628216.6667, "Xij": 30520133.333, "EpiMreg": 210842.41456, "BubbleSizeMreg": 2568628.9026, "LineWithMreg": 0.0018518474, "Gap": 1.0, "Rank": 7}, {"ItemCode": "699", "ParentCode": "13", "Item": {"Code": "699", "Name": "India", "ParentCode": 13, "Parent": {"Code": "13", "Name": "South Asia", "ParentCode": 0, "Color": "#dac20c"}}, "Value": 31340.06826, "ExportValue": 783766.66667, "RealizedPotential": 1.0, "LineLength": 43.762093021, "BubbleSize": 569368.96153, "LineWidth": 0.6069488105, "Ta": 0.0, "Stability": 0.0, "Tariff": 0.15, "Xik": 170247666.67, "Mjk": 1628216.6667, "Xij": 66485866.667, "EpiMreg": 237265.18445, "BubbleSizeMreg": 3092819.7202, "LineWithMreg": 0.0017529976, "Gap": 0.0, "Rank": 8}, {"ItemCode": "328", "ParentCode": "2", "Item": {"Code": "328", "Name": "Guyana", "ParentCode": 2, "Parent": {"Code": "2", "Name": "Caribbean", "ParentCode": 0, "Color": "#816dbf"}}, "Value": 30716.66489, "ExportValue": 0.0, "RealizedPotential": 0.0, "LineLength": 300.18914818, "BubbleSize": 266136.8752, "LineWidth": 0.1855316546, "Ta": 0.0, "Stability": 0.0, "Tariff": 0.15, "Xik": 123841366.67, "Mjk": 1628216.6667, "Xij": 14800.0, "EpiMreg": 116821.62926, "BubbleSizeMreg": 1624386.2992, "LineWithMreg": 0.0002395736, "Gap": 1.0, "Rank": 9}, {"ItemCode": "826", "ParentCode": "4", "Item": {"Code": "826", "Name": "United Kingdom", "ParentCode": 4, "Parent": {"Code": "4", "Name": "EU & West Europe", "ParentCode": 0, "Color": "#3d8fc3"}}, "Value": 16053.235857, "ExportValue": 500.0, "RealizedPotential": 0.0311463685, "LineLength": 2.8117090461, "BubbleSize": 681832.0324, "LineWidth": 4.0407204705, "Ta": 0.0, "Stability": 0.0, "Tariff": 0.15, "Xik": 5464900.0, "Mjk": 1628216.6667, "Xij": 630750500.0, "EpiMreg": 26847.949829, "BubbleSizeMreg": 2821873.4421, "LineWithMreg": 0.0033837886, "Gap": 0.9688536315, "Rank": 10}, {"ItemCode": "528", "ParentCode": "4", "Item": {"Code": "528", "Name": "Netherlands", "ParentCode": 4, "Parent": {"Code": "4", "Name": "EU & West Europe", "ParentCode": 0, "Color": "#3d8fc3"}}, "Value": 12486.643274, "ExportValue": 466.66666667, "RealizedPotential": 0.0373732681, "LineLength": 10.444779488, "BubbleSize": 606444.48658, "LineWidth": 0.9512603106, "Ta": 0.0, "Stability": 0.0, "Tariff": 0.15, "Xik": 22691433.333, "Mjk": 1628216.6667, "Xij": 158890366.67, "EpiMreg": 56978.605217, "BubbleSizeMreg": 2738241.2904, "LineWithMreg": 0.0019922362, "Gap": 0.9626267319, "Rank": 11}, {"ItemCode": "56", "ParentCode": "4", "Item": {"Code": "56", "Name": "Belgium", "ParentCode": 4, "Parent": {"Code": "4", "Name": "EU & West Europe", "ParentCode": 0, "Color": "#3d8fc3"}}, "Value": 7588.0360727, "ExportValue": 0.0, "RealizedPotential": 0.0, "LineLength": 14.234886238, "BubbleSize": 614831.1533, "LineWidth": 0.4183728765, "Ta": 0.0, "Stability": 0.0, "Tariff": 0.15, "Xik": 27785100.0, "Mjk": 1628216.6667, "Xij": 60274200.0, "EpiMreg": 60047.657632, "BubbleSizeMreg": 2797235.611, "LineWithMreg": 0.0015080406, "Gap": 1.0, "Rank": 12}, {"ItemCode": "600", "ParentCode": "8", "Item": {"Code": "600", "Name": "Paraguay", "ParentCode": 8, "Parent": {"Code": "8", "Name": "Latin America", "ParentCode": 0, "Color": "#924688"}}, "Value": 7320.8888354, "ExportValue": 0.0, "RealizedPotential": 0.0, "LineLength": 25.172418694, "BubbleSize": 222559.4622, "LineWidth": 0.630575078, "Ta": 0.0, "Stability": 0.0, "Tariff": 0.15, "Xik": 40102333.333, "Mjk": 1628216.6667, "Xij": 399666.66667, "EpiMreg": 297936.86098, "BubbleSizeMreg": 1309230.5662, "LineWithMreg": 0.0090403065, "Gap": 1.0, "Rank": 13}, {"ItemCode": "276", "ParentCode": "4", "Item": {"Code": "276", "Name": "Germany", "ParentCode": 4, "Parent": {"Code": "4", "Name": "EU & West Europe", "ParentCode": 0, "Color": "#3d8fc3"}}, "Value": 6938.5773834, "ExportValue": 266.66666667, "RealizedPotential": 0.0384324699, "LineLength": 6.552682522, "BubbleSize": 548926.88943, "LineWidth": 0.9308523593, "Ta": 0.0, "Stability": 0.0, "Tariff": 0.15, "Xik": 13940400.0, "Mjk": 1628216.6667, "Xij": 551571633.33, "EpiMreg": 49415.533073, "BubbleSizeMreg": 2682599.2196, "LineWithMreg": 0.0028111794, "Gap": 0.9615675301, "Rank": 14}, {"ItemCode": "300", "ParentCode": "4", "Item": {"Code": "300", "Name": "Greece", "ParentCode": 4, "Parent": {"Code": "4", "Name": "EU & West Europe", "ParentCode": 0, "Color": "#3d8fc3"}}, "Value": 6870.6562029, "ExportValue": 0.0, "RealizedPotential": 0.0, "LineLength": 10.120283846, "BubbleSize": 373626.99551, "LineWidth": 0.8768216741, "Ta": 0.0, "Stability": 0.0, "Tariff": 0.15, "Xik": 9629100.0, "Mjk": 1628216.6667, "Xij": 12660333.333, "EpiMreg": 334711.52235, "BubbleSizeMreg": 2703342.6073, "LineWithMreg": 0.0122342367, "Gap": 1.0, "Rank": 15}, {"ItemCode": "104", "ParentCode": "1", "Item": {"Code": "104", "Name": "Myanmar", "ParentCode": 1, "Parent": {"Code": "1", "Name": "ASEAN", "ParentCode": 0, "Color": "#54A2C9"}}, "Value": 6268.9105285, "ExportValue": 0.0, "RealizedPotential": 0.0, "LineLength": 10.685860337, "BubbleSize": 567698.27358, "LineWidth": 0.4986651343, "Ta": 0.0, "Stability": 0.0, "Tariff": 0.15, "Xik": 4186071.7949, "Mjk": 1628216.6667, "Xij": 701000.0, "EpiMreg": 39804.323402, "BubbleSizeMreg": 3744051.1493, "LineWithMreg": 0.000994899, "Gap": 1.0, "Rank": 16}, {"ItemCode": "643", "ParentCode": "6", "Item": {"Code": "643", "Name": "Russian Federation", "ParentCode": 6, "Parent": {"Code": "6", "Name": "East Europe & Central Asia", "ParentCode": 0, "Color": "#C0392B"}}, "Value": 6265.716972, "ExportValue": 26166.666667, "RealizedPotential": 1.0, "LineLength": 0.4948214389, "BubbleSize": 642160.66011, "LineWidth": 9.515301838, "Ta": 0.0, "Stability": 0.0, "Tariff": 0.0, "Xik": 692866.66667, "Mjk": 1628216.6667, "Xij": 1820667733.3, "EpiMreg": 68416.055098, "BubbleSizeMreg": 2581150.073, "LineWithMreg": 0.0535668693, "Gap": 0.0, "Rank": 17}, {"ItemCode": "32", "ParentCode": "8", "Item": {"Code": "32", "Name": "Argentina", "ParentCode": 8, "Parent": {"Code": "8", "Name": "Latin America", "ParentCode": 0, "Color": "#924688"}}, "Value": 6211.1326979, "ExportValue": 0.0, "RealizedPotential": 0.0, "LineLength": 12.816786801, "BubbleSize": 210536.08449, "LineWidth": 1.1107315444, "Ta": 0.0, "Stability": 0.0, "Tariff": 0.15, "Xik": 21615233.333, "Mjk": 1628216.6667, "Xij": 9594566.6667, "EpiMreg": 52894.113723, "BubbleSizeMreg": 1236191.7363, "LineWithMreg": 0.0033384306, "Gap": 1.0, "Rank": 18}, {"ItemCode": "100", "ParentCode": "4", "Item": {"Code": "100", "Name": "Bulgaria", "ParentCode": 4, "Parent": {"Code": "4", "Name": "EU & West Europe", "ParentCode": 0, "Color": "#3d8fc3"}}, "Value": 5990.9488861, "ExportValue": 0.0, "RealizedPotential": 0.0, "LineLength": 7.9269430679, "BubbleSize": 340222.6061, "LineWidth": 1.0719405703, "Ta": 0.0, "Stability": 0.0, "Tariff": 0.15, "Xik": 5380333.3333, "Mjk": 1628216.6667, "Xij": 26882800.0, "EpiMreg": 256362.24345, "BubbleSizeMreg": 2226848.7893, "LineWithMreg": 0.0145230421, "Gap": 1.0, "Rank": 19}, {"ItemCode": "76", "ParentCode": "8", "Item": {"Code": "76", "Name": "Brazil", "ParentCode": 8, "Parent": {"Code": "8", "Name": "Latin America", "ParentCode": 0, "Color": "#924688"}}, "Value": 3673.3574978, "ExportValue": 0.0, "RealizedPotential": 0.0, "LineLength": 3.5537281349, "BubbleSize": 251977.8271, "LineWidth": 1.979523535, "Ta": 0.0, "Stability": 0.0, "Tariff": 0.15, "Xik": 4007766.6667, "Mjk": 1628216.6667, "Xij": 95262066.667, "EpiMreg": 16220.527805, "BubbleSizeMreg": 1488760.4571, "LineWithMreg": 0.0030658857, "Gap": 1.0, "Rank": 20}, {"ItemCode": "251", "ParentCode": "4", "Item": {"Code": "251", "Name": "France", "ParentCode": 4, "Parent": {"Code": "4", "Name": "EU & West Europe", "ParentCode": 0, "Color": "#3d8fc3"}}, "Value": 3433.0257624, "ExportValue": 166.66666667, "RealizedPotential": 0.0485480384, "LineLength": 3.2574181789, "BubbleSize": 634772.42922, "LineWidth": 0.8011788784, "Ta": 0.0, "Stability": 0.0, "Tariff": 0.15, "Xik": 6250533.3333, "Mjk": 1628216.6667, "Xij": 162470466.67, "EpiMreg": 18665.403363, "BubbleSizeMreg": 2929679.189, "LineWithMreg": 0.0019558872, "Gap": 0.9514519616, "Rank": 21}, {"ItemCode": "642", "ParentCode": "4", "Item": {"Code": "642", "Name": "Romania", "ParentCode": 4, "Parent": {"Code": "4", "Name": "EU & West Europe", "ParentCode": 0, "Color": "#3d8fc3"}}, "Value": 3163.1329012, "ExportValue": 0.0, "RealizedPotential": 0.0, "LineLength": 3.6632357108, "BubbleSize": 341556.8641, "LineWidth": 1.2199261972, "Ta": 0.0, "Stability": 0.0, "Tariff": 0.15, "Xik": 1879500.0, "Mjk": 1628216.6667, "Xij": 55082833.333, "EpiMreg": 96770.439063, "BubbleSizeMreg": 2330957.4336, "LineWithMreg": 0.0113329639, "Gap": 1.0, "Rank": 22}, {"ItemCode": "392", "ParentCode": "5", "Item": {"Code": "392", "Name": "Japan", "ParentCode": 5, "Parent": {"Code": "5", "Name": "East Asia", "ParentCode": 0, "Color": "#d8a618"}}, "Value": 2948.9940158, "ExportValue": 0.0, "RealizedPotential": 0.0, "LineLength": 3.6859517457, "BubbleSize": 391665.93344, "LineWidth": 0.9857174548, "Ta": 0.0, "Stability": 0.0, "Tariff": 0.15, "Xik": 7085500.0, "Mjk": 1628216.6667, "Xij": 162655833.33, "EpiMreg": 17130.864643, "BubbleSizeMreg": 2353091.1223, "LineWithMreg": 0.0019751082, "Gap": 1.0, "Rank": 23}, {"ItemCode": "144", "ParentCode": "13", "Item": {"Code": "144", "Name": "Sri Lanka", "ParentCode": 13, "Parent": {"Code": "13", "Name": "South Asia", "ParentCode": 0, "Color": "#dac20c"}}, "Value": 2906.542783, "ExportValue": 0.0, "RealizedPotential": 0.0, "LineLength": 0.5585396847, "BubbleSize": 607643.07708, "LineWidth": 4.1325501257, "Ta": 0.0, "Stability": 0.0, "Tariff": 0.15, "Xik": 880600.0, "Mjk": 1628216.6667, "Xij": 50079166.667, "EpiMreg": 5635.9516861, "BubbleSizeMreg": 2990068.7951, "LineWithMreg": 0.0033746757, "Gap": 1.0, "Rank": 24}, {"ItemCode": "792", "ParentCode": "9", "Item": {"Code": "792", "Name": "Turkey", "ParentCode": 9, "Parent": {"Code": "9", "Name": "Middle East", "ParentCode": 0, "Color": "#b69118"}}, "Value": 2521.4192481, "ExportValue": 16500.0, "RealizedPotential": 1.0, "LineLength": 0.3929899829, "BubbleSize": 230712.60619, "LineWidth": 13.419497632, "Ta": 0.0, "Stability": 0.0, "Tariff": 0.15, "Xik": 1147500.0, "Mjk": 1628216.6667, "Xij": 1550056500.0, "EpiMreg": 9412.3726336, "BubbleSizeMreg": 2271885.402, "LineWithMreg": 0.010542199, "Gap": 0.0, "Rank": 25}, {"ItemCode": "116", "ParentCode": "1", "Item": {"Code": "116", "Name": "Cambodia", "ParentCode": 1, "Parent": {"Code": "1", "Name": "ASEAN", "ParentCode": 0, "Color": "#54A2C9"}}, "Value": 1973.385255, "ExportValue": 1250.0, "RealizedPotential": 0.6334292794, "LineLength": 2.1855597227, "BubbleSize": 464486.29312, "LineWidth": 0.9380377098, "Ta": 0.0, "Stability": 0.0, "Tariff": 0.15, "Xik": 2816783.3333, "Mjk": 1628216.6667, "Xij": 2860416.6667, "EpiMreg": 12951.162241, "BubbleSizeMreg": 3157988.9376, "LineWithMreg": 0.0018764434, "Gap": 0.36657072059999996, "Rank": 26}, {"ItemCode": "418", "ParentCode": "1", "Item": {"Code": "418", "Name": "Lao People's Democratic Republic", "ParentCode": 1, "Parent": {"Code": "1", "Name": "ASEAN", "ParentCode": 0, "Color": "#54A2C9"}}, "Value": 1812.9171958, "ExportValue": 0.0, "RealizedPotential": 0.0, "LineLength": 30.447414992, "BubbleSize": 505874.62544, "LineWidth": 0.0567974249, "Ta": 0.0, "Stability": 0.0, "Tariff": 0.15, "Xik": 12597633.333, "Mjk": 1628216.6667, "Xij": 20416.666667, "EpiMreg": 39716.059178, "BubbleSizeMreg": 3276424.3881, "LineWithMreg": 0.0003981214, "Gap": 1.0, "Rank": 27}, {"ItemCode": "50", "ParentCode": "13", "Item": {"Code": "50", "Name": "Bangladesh", "ParentCode": 13, "Parent": {"Code": "13", "Name": "South Asia", "ParentCode": 0, "Color": "#dac20c"}}, "Value": 1261.6353667, "ExportValue": 0.0, "RealizedPotential": 0.0, "LineLength": 1.0074051127, "BubbleSize": 679592.75825, "LineWidth": 0.8892522275, "Ta": 0.0, "Stability": 0.0, "Tariff": 0.15, "Xik": 1269750.0, "Mjk": 1628216.6667, "Xij": 8907142.8571, "EpiMreg": 9959.8048633, "BubbleSizeMreg": 3974888.0698, "LineWithMreg": 0.0024872634, "Gap": 1.0, "Rank": 28}, {"ItemCode": "784", "ParentCode": "9", "Item": {"Code": "784", "Name": "United Arab Emirates", "ParentCode": 9, "Parent": {"Code": "9", "Name": "Middle East", "ParentCode": 0, "Color": "#b69118"}}, "Value": 1197.6841782, "ExportValue": 2400.0, "RealizedPotential": 1.0, "LineLength": 0.6231907734, "BubbleSize": 310213.35798, "LineWidth": 2.9895429875, "Ta": 0.0, "Stability": 0.0, "Tariff": 0.15, "Xik": 881000.0, "Mjk": 1628216.6667, "Xij": 187137666.67, "EpiMreg": 4174.2391514, "BubbleSizeMreg": 2444701.0356, "LineWithMreg": 0.0027398738, "Gap": 0.0, "Rank": 29}, {"ItemCode": "616", "ParentCode": "4", "Item": {"Code": "616", "Name": "Poland", "ParentCode": 4, "Parent": {"Code": "4", "Name": "EU & West Europe", "ParentCode": 0, "Color": "#3d8fc3"}}, "Value": 901.2632408, "ExportValue": 0.0, "RealizedPotential": 0.0, "LineLength": 1.198708266, "BubbleSize": 440791.04, "LineWidth": 0.823093932, "Ta": 0.0, "Stability": 0.0, "Tariff": 0.15, "Xik": 2674833.3333, "Mjk": 1628216.6667, "Xij": 86760500.0, "EpiMreg": 15270.46536, "BubbleSizeMreg": 2442743.3037, "LineWithMreg": 0.0052150796, "Gap": 1.0, "Rank": 30}, {"ItemCode": "36", "ParentCode": "12", "Item": {"Code": "36", "Name": "Australia", "ParentCode": 12, "Parent": {"Code": "12", "Name": "Pacific", "ParentCode": 0, "Color": "#309d6d"}}, "Value": 867.60015032, "ExportValue": 0.0, "RealizedPotential": 0.0, "LineLength": 12.749149573, "BubbleSize": 227701.76257, "LineWidth": 0.1442168515, "Ta": 0.0, "Stability": 0.0, "Tariff": 0.15, "Xik": 10390400.0, "Mjk": 1628216.6667, "Xij": 4815633.3333, "EpiMreg": 16198.389036, "BubbleSizeMreg": 1202803.1556, "LineWithMreg": 0.0010563213, "Gap": 1.0, "Rank": 31}, {"ItemCode": "620", "ParentCode": "4", "Item": {"Code": "620", "Name": "Portugal", "ParentCode": 4, "Parent": {"Code": "4", "Name": "EU & West Europe", "ParentCode": 0, "Color": "#3d8fc3"}}, "Value": 721.44780022, "ExportValue": 0.0, "RealizedPotential": 0.0, "LineLength": 1.3288924978, "BubbleSize": 598075.16589, "LineWidth": 0.4380294339, "Ta": 0.0, "Stability": 0.0, "Tariff": 0.15, "Xik": 2408600.0, "Mjk": 1628216.6667, "Xij": 7690333.3333, "EpiMreg": 3959.1505814, "BubbleSizeMreg": 2879722.8475, "LineWithMreg": 0.0010345738, "Gap": 1.0, "Rank": 32}, {"ItemCode": "858", "ParentCode": "8", "Item": {"Code": "858", "Name": "Uruguay", "ParentCode": 8, "Parent": {"Code": "8", "Name": "Latin America", "ParentCode": 0, "Color": "#924688"}}, "Value": 680.58135464, "ExportValue": 0.0, "RealizedPotential": 0.0, "LineLength": 34.617823913, "BubbleSize": 214933.15389, "LineWidth": 0.0441388355, "Ta": 0.0, "Stability": 0.0, "Tariff": 0.15, "Xik": 44431366.667, "Mjk": 1628216.6667, "Xij": 173933.33333, "EpiMreg": 90733.161855, "BubbleSizeMreg": 1255396.26, "LineWithMreg": 0.0020877834, "Gap": 1.0, "Rank": 33}, {"ItemCode": "208", "ParentCode": "4", "Item": {"Code": "208", "Name": "Denmark", "ParentCode": 4, "Parent": {"Code": "4", "Name": "EU & West Europe", "ParentCode": 0, "Color": "#3d8fc3"}}, "Value": 641.04980382, "ExportValue": 0.0, "RealizedPotential": 0.0, "LineLength": 0.9579038686, "BubbleSize": 549509.01149, "LineWidth": 0.5876774486, "Ta": 0.0, "Stability": 0.0, "Tariff": 0.15, "Xik": 1954533.3333, "Mjk": 1628216.6667, "Xij": 22029833.333, "EpiMreg": 4031.3677256, "BubbleSizeMreg": 2485032.7893, "LineWithMreg": 0.0016935513, "Gap": 1.0, "Rank": 34}, {"ItemCode": "490", "ParentCode": "5", "Item": {"Code": "490", "Name": "Taipei, Chinese", "ParentCode": 5, "Parent": {"Code": "5", "Name": "East Asia", "ParentCode": 0, "Color": "#d8a618"}}, "Value": 576.89557528, "ExportValue": 0.0, "RealizedPotential": 0.0, "LineLength": 2.780210878, "BubbleSize": 426958.50008, "LineWidth": 0.2345188768, "Ta": 0.0, "Stability": 0.0, "Tariff": 0.15, "Xik": 1277833.3333, "Mjk": 1628216.6667, "Xij": 9105200.0, "EpiMreg": 6693.1457112, "BubbleSizeMreg": 2374414.7195, "LineWithMreg": 0.001013902, "Gap": 1.0, "Rank": 35}, {"ItemCode": "203", "ParentCode": "4", "Item": {"Code": "203", "Name": "Czechia", "ParentCode": 4, "Parent": {"Code": "4", "Name": "EU & West Europe", "ParentCode": 0, "Color": "#3d8fc3"}}, "Value": 560.82824018, "ExportValue": 0.0, "RealizedPotential": 0.0, "LineLength": 0.4122284586, "BubbleSize": 476794.77561, "LineWidth": 1.3769063906, "Ta": 0.0, "Stability": 0.0, "Tariff": 0.15, "Xik": 922833.33333, "Mjk": 1628216.6667, "Xij": 96463100.0, "EpiMreg": 4967.1871255, "BubbleSizeMreg": 2631542.9151, "LineWithMreg": 0.0045789099, "Gap": 1.0, "Rank": 36}, {"ItemCode": "710", "ParentCode": "14", "Item": {"Code": "710", "Name": "South Africa", "ParentCode": 14, "Parent": {"Code": "14", "Name": "Southern Africa", "ParentCode": 0, "Color": "#DB4C60"}}, "Value": 359.84153294, "ExportValue": 0.0, "RealizedPotential": 0.0, "LineLength": 0.4789994471, "BubbleSize": 362377.88137, "LineWidth": 1.0003652439, "Ta": 0.0, "Stability": 0.0, "Tariff": 0.15, "Xik": 864633.33333, "Mjk": 1628216.6667, "Xij": 32597000.0, "EpiMreg": 1516.5585239, "BubbleSizeMreg": 1901225.4068, "LineWithMreg": 0.0016652926, "Gap": 1.0, "Rank": 37}, {"ItemCode": "682", "ParentCode": "9", "Item": {"Code": "682", "Name": "Saudi Arabia", "ParentCode": 9, "Parent": {"Code": "9", "Name": "Middle East", "ParentCode": 0, "Color": "#b69118"}}, "Value": 304.22795879, "ExportValue": 0.0, "RealizedPotential": 0.0, "LineLength": 1.1344916863, "BubbleSize": 325675.88953, "LineWidth": 0.3973344286, "Ta": 0.0, "Stability": 0.0, "Tariff": 0.15, "Xik": 2195866.6667, "Mjk": 1628216.6667, "Xij": 8904233.3333, "EpiMreg": 2334.9716954, "BubbleSizeMreg": 2401272.0903, "LineWithMreg": 0.0008571147, "Gap": 1.0, "Rank": 38}, {"ItemCode": "458", "ParentCode": "1", "Item": {"Code": "458", "Name": "Malaysia", "ParentCode": 1, "Parent": {"Code": "1", "Name": "ASEAN", "ParentCode": 0, "Color": "#54A2C9"}}, "Value": 79.058019625, "ExportValue": 0.0, "RealizedPotential": 0.0, "LineLength": 0.1114590737, "BubbleSize": 426213.69306, "LineWidth": 0.8030583525, "Ta": 0.0, "Stability": 0.0, "Tariff": 0.15, "Xik": 164966.66667, "Mjk": 1628216.6667, "Xij": 33682300.0, "EpiMreg": 379.25614321, "BubbleSizeMreg": 2298840.5252, "LineWithMreg": 0.0014801589, "Gap": 1.0, "Rank": 39}, {"ItemCode": "702", "ParentCode": "1", "Item": {"Code": "702", "Name": "Singapore", "ParentCode": 1, "Parent": {"Code": "1", "Name": "ASEAN", "ParentCode": 0, "Color": "#54A2C9"}}, "Value": 74.561318741, "ExportValue": 0.0, "RealizedPotential": 0.0, "LineLength": 0.1729316448, "BubbleSize": 414816.75954, "LineWidth": 0.5015645273, "Ta": 0.0, "Stability": 0.0, "Tariff": 0.15, "Xik": 233000.0, "Mjk": 1628216.6667, "Xij": 73413866.667, "EpiMreg": 327.34670556, "BubbleSizeMreg": 2234239.7628, "LineWithMreg": 0.0008472347, "Gap": 1.0, "Rank": 40}, {"ItemCode": "807", "ParentCode": "6", "Item": {"Code": "807", "Name": "Macedonia, North", "ParentCode": 6, "Parent": {"Code": "6", "Name": "East Europe & Central Asia", "ParentCode": 0, "Color": "#C0392B"}}, "Value": 50.999495103, "ExportValue": 0.0, "RealizedPotential": 0.0, "LineLength": 0.2716412386, "BubbleSize": 390907.28878, "LineWidth": 0.2317610268, "Ta": 0.0, "Stability": 0.0, "Tariff": 0.15, "Xik": 444166.66667, "Mjk": 1628216.6667, "Xij": 590266.66667, "EpiMreg": 29765.236727, "BubbleSizeMreg": 2128175.9906, "LineWithMreg": 0.0514880091, "Gap": 1.0, "Rank": 41}, {"ItemCode": "360", "ParentCode": "1", "Item": {"Code": "360", "Name": "Indonesia", "ParentCode": 1, "Parent": {"Code": "1", "Name": "ASEAN", "ParentCode": 0, "Color": "#54A2C9"}}, "Value": 45.499220918, "ExportValue": 0.0, "RealizedPotential": 0.0, "LineLength": 0.0560735341, "BubbleSize": 372153.44437, "LineWidth": 1.0521265713, "Ta": 0.0, "Stability": 0.0, "Tariff": 0.15, "Xik": 82666.666667, "Mjk": 1628216.6667, "Xij": 33299800.0, "EpiMreg": 266.30782173, "BubbleSizeMreg": 2016790.5635, "LineWithMreg": 0.0023548605, "Gap": 1.0, "Rank": 42}, {"ItemCode": "384", "ParentCode": "15", "Item": {"Code": "384", "Name": "C\u00f4te d'Ivoire", "ParentCode": 15, "Parent": {"Code": "15", "Name": "Western Africa", "ParentCode": 0, "Color": "#dab911"}}, "Value": 19.202491521, "ExportValue": 0.0, "RealizedPotential": 0.0, "LineLength": 0.5807991674, "BubbleSize": 445982.29276, "LineWidth": 0.0357732157, "Ta": 0.0, "Stability": 0.0, "Tariff": 0.15, "Xik": 743600.0, "Mjk": 1628216.6667, "Xij": 30066.666667, "EpiMreg": 1629.0482912, "BubbleSizeMreg": 2535687.4514, "LineWithMreg": 0.0011061455, "Gap": 1.0, "Rank": 43}]